{
  "x-ig-www-claim": "hmac.AR10tAZemMeMaHV4EiNr7MdZIiOnhDZBNXV4vSWqakpqQXk9",
  "user-agent": "Mozilla/5.0 (Windows NT 10.0; Win64; x64) AppleWebKit/537.36 (KHTML, like Gecko) Chrome/88.0.4324.182 Safari/537.36",
  "viewport-width": "1366",
  "accept": "*/*",
  "referer": "https://www.instagram.com/virat.kohli/",
  "x-requested-with": "XMLHttpRequest",
  "x-asbd-id": "129477",
  "x-csrftoken": "9FYKJjunoBdcM5Ho5V4YOMTz2mUHnv4K",
  "sec-ch-prefers-color-scheme": "light",
  "x-ig-app-id": "936619743392459",
  "cookie": "sessionid=60925082005%3A9cSB27vnfQ4b32%3A2%3AAYf29RjcncteG3wIbJ-2NXy0yQvlBC5zqfVziaUmGg; mid=ZNPwmgALAAGxgNcghdRXwYvNo7w4; csrftoken=9FYKJjunoBdcM5Ho5V4YOMTz2mUHnv4K; ig_nrcb=1; datr=mfDTZHZtriag-9Lt0Va2JY5J; ds_user_id=60925082005; ig_did=5D16162F-6326-491B-B10C-FBC0301FD84C; rur=\"PRN\\05460925082005\\0541723147431:01f71d67c04cc59eeeb6fdf737ad0bc7439d69a072757a8f3b54ab224ea1ccdb2fcedd2b\""
}